wunderkafka/__init__.py
wunderkafka/compat.py
wunderkafka/errors.py
wunderkafka/librdkafka.py
wunderkafka/logger.py
wunderkafka/message.py
wunderkafka/protocols.py
wunderkafka/py.typed
wunderkafka/structures.py
wunderkafka/time.py
wunderkafka/types.py
wunderkafka/callbacks/__init__.py
wunderkafka/callbacks/producer.py
wunderkafka/callbacks/auth/__init__.py
wunderkafka/callbacks/auth/iam.py
wunderkafka/callbacks/consumer/__init__.py
wunderkafka/callbacks/consumer/subscribe.py
wunderkafka/config/__init__.py
wunderkafka/config/generate.py
wunderkafka/config/protocols.py
wunderkafka/config/rdkafka.py
wunderkafka/config/schema_registry.py
wunderkafka/config/generated/enums.py
wunderkafka/config/generated/fields.py
wunderkafka/config/generated/models.py
wunderkafka/config/generated/v2_0_0/enums.py
wunderkafka/config/generated/v2_0_0/fields.py
wunderkafka/config/generated/v2_0_0/models.py
wunderkafka/config/generated/v2_10_0/enums.py
wunderkafka/config/generated/v2_10_0/fields.py
wunderkafka/config/generated/v2_10_0/models.py
wunderkafka/config/generated/v2_11_0/enums.py
wunderkafka/config/generated/v2_11_0/fields.py
wunderkafka/config/generated/v2_11_0/models.py
wunderkafka/config/generated/v2_12_0/enums.py
wunderkafka/config/generated/v2_12_0/fields.py
wunderkafka/config/generated/v2_12_0/models.py
wunderkafka/config/generated/v2_1_0/enums.py
wunderkafka/config/generated/v2_1_0/fields.py
wunderkafka/config/generated/v2_1_0/models.py
wunderkafka/config/generated/v2_2_0/enums.py
wunderkafka/config/generated/v2_2_0/fields.py
wunderkafka/config/generated/v2_2_0/models.py
wunderkafka/config/generated/v2_3_0/enums.py
wunderkafka/config/generated/v2_3_0/fields.py
wunderkafka/config/generated/v2_3_0/models.py
wunderkafka/config/generated/v2_4_0/enums.py
wunderkafka/config/generated/v2_4_0/fields.py
wunderkafka/config/generated/v2_4_0/models.py
wunderkafka/config/generated/v2_5_0/enums.py
wunderkafka/config/generated/v2_5_0/fields.py
wunderkafka/config/generated/v2_5_0/models.py
wunderkafka-0.20.0.dist-info/licenses/LICENSE
wunderkafka-0.20.0.dist-info/METADATA
wunderkafka-0.20.0.dist-info/WHEEL
wunderkafka-0.20.0.dist-info/top_level.txt
wunderkafka-0.20.0.dist-info/RECORD
