Metadata-Version: 2.4
Name: wunderkafka
Version: 0.20.0
Summary: librdkafka-powered client for Kafka for python with (hopefully) more handful API
Author-email: Kirill Tribunsky <tribunsky.kir@yandex.ru>
License: Apache-2.0
Project-URL: Homepage, https://github.com/wunderkafka/wunderkafka
Project-URL: Bug Tracker, https://github.com/wunderkafka/wunderkafka/issues
Keywords: kafka,cloudera,confluent
Classifier: Development Status :: 4 - Beta
Classifier: Programming Language :: Python :: 3
Classifier: Programming Language :: Python :: 3 :: Only
Classifier: License :: OSI Approved :: Apache Software License
Classifier: Operating System :: POSIX :: Linux
Classifier: Intended Audience :: Developers
Classifier: Topic :: Software Development :: Libraries :: Python Modules
Requires-Python: >=3.9
License-File: LICENSE
Requires-Dist: confluent-kafka[schema-registry]>=1.9.0
Requires-Dist: avro-python3>=1.10.0
Requires-Dist: dataclasses-avroschema[pydantic]>=0.53.0
Requires-Dist: fastavro>=1.4.7
Requires-Dist: pydantic-settings>2.0
Requires-Dist: pydantic>=2.7.0
Requires-Dist: setuptools>=80.3.1
Requires-Dist: orjson>=3.10.0
Provides-Extra: krb
Requires-Dist: requests-kerberos>=0.13.0; extra == "krb"
Requires-Dist: python-dateutil; extra == "krb"
Provides-Extra: json
Requires-Dist: jsonschema>=4.17.3; extra == "json"
Provides-Extra: iam
Requires-Dist: aws-msk-iam-sasl-signer-python>=1.0.2; extra == "iam"
Dynamic: license-file
